app/commander/config_pb2.py
app/commander/config_pb2_grpc.py
app/dispatcher/config_pb2.py
app/dispatcher/config_pb2_grpc.py
app/dns/config_pb2.py
app/dns/config_pb2_grpc.py
app/dns/fakedns/fakedns_pb2.py
app/dns/fakedns/fakedns_pb2_grpc.py
app/log/config_pb2.py
app/log/config_pb2_grpc.py
app/log/command/config_pb2.py
app/log/command/config_pb2_grpc.py
app/metrics/config_pb2.py
app/metrics/config_pb2_grpc.py
app/observatory/config_pb2.py
app/observatory/config_pb2_grpc.py
app/observatory/burst/config_pb2.py
app/observatory/burst/config_pb2_grpc.py
app/observatory/command/command_pb2.py
app/observatory/command/command_pb2_grpc.py
app/policy/config_pb2.py
app/policy/config_pb2_grpc.py
app/proxyman/config_pb2.py
app/proxyman/config_pb2_grpc.py
app/proxyman/command/command_pb2.py
app/proxyman/command/command_pb2_grpc.py
app/reverse/config_pb2.py
app/reverse/config_pb2_grpc.py
app/router/config_pb2.py
app/router/config_pb2_grpc.py
app/router/command/command_pb2.py
app/router/command/command_pb2_grpc.py
app/stats/config_pb2.py
app/stats/config_pb2_grpc.py
app/stats/command/command_pb2.py
app/stats/command/command_pb2_grpc.py
app/version/config_pb2.py
app/version/config_pb2_grpc.py
common/log/log_pb2.py
common/log/log_pb2_grpc.py
common/net/address_pb2.py
common/net/address_pb2_grpc.py
common/net/destination_pb2.py
common/net/destination_pb2_grpc.py
common/net/network_pb2.py
common/net/network_pb2_grpc.py
common/net/port_pb2.py
common/net/port_pb2_grpc.py
common/protocol/headers_pb2.py
common/protocol/headers_pb2_grpc.py
common/protocol/server_spec_pb2.py
common/protocol/server_spec_pb2_grpc.py
common/protocol/user_pb2.py
common/protocol/user_pb2_grpc.py
common/serial/typed_message_pb2.py
common/serial/typed_message_pb2_grpc.py
core/config_pb2.py
core/config_pb2_grpc.py
proxy/blackhole/config_pb2.py
proxy/blackhole/config_pb2_grpc.py
proxy/dns/config_pb2.py
proxy/dns/config_pb2_grpc.py
proxy/dokodemo/config_pb2.py
proxy/dokodemo/config_pb2_grpc.py
pyraycore-25.12.8.dist-info/METADATA
pyraycore-25.12.8.dist-info/WHEEL
pyraycore-25.12.8.dist-info/entry_points.txt
pyraycore-25.12.8.dist-info/top_level.txt
pyraycore-25.12.8.dist-info/RECORD
