Metadata-Version: 2.4
Name: pyraycore
Version: 25.12.8
Summary: Python gRPC bindings for Xray-core — control and monitor VLESS, REALITY and other protocols via gRPC API.
Author: Роман (ex3lite)
License: MIT
Project-URL: Homepage, https://github.com/ex3lite/pyraycore
Project-URL: Repository, https://github.com/ex3lite/pyraycore
Project-URL: Issues, https://github.com/ex3lite/pyraycore/issues
Requires-Python: >=3.10
Requires-Dist: grpcio>=1.65.0
Requires-Dist: protobuf>=5.28.0
